odoo/addons/stock_picking_batch_extended/README.rst
odoo/addons/stock_picking_batch_extended/__init__.py
odoo/addons/stock_picking_batch_extended/__manifest__.py
odoo/addons/stock_picking_batch_extended/data/batch_picking_actions_server.xml
odoo/addons/stock_picking_batch_extended/data/stock_batch_picking_sequence.xml
odoo/addons/stock_picking_batch_extended/i18n/de.po
odoo/addons/stock_picking_batch_extended/i18n/es.po
odoo/addons/stock_picking_batch_extended/i18n/es_CL.po
odoo/addons/stock_picking_batch_extended/i18n/fr.po
odoo/addons/stock_picking_batch_extended/i18n/it.po
odoo/addons/stock_picking_batch_extended/i18n/pt_BR.po
odoo/addons/stock_picking_batch_extended/i18n/sl.po
odoo/addons/stock_picking_batch_extended/i18n/stock_picking_batch_extended.pot
odoo/addons/stock_picking_batch_extended/migrations/12.0.1.0.0/post-migration.py
odoo/addons/stock_picking_batch_extended/migrations/12.0.1.0.0/pre-migration.py
odoo/addons/stock_picking_batch_extended/models/__init__.py
odoo/addons/stock_picking_batch_extended/models/product_product.py
odoo/addons/stock_picking_batch_extended/models/res_config_settings.py
odoo/addons/stock_picking_batch_extended/models/stock_batch_picking.py
odoo/addons/stock_picking_batch_extended/models/stock_picking.py
odoo/addons/stock_picking_batch_extended/models/stock_warehouse.py
odoo/addons/stock_picking_batch_extended/readme/CONTRIBUTORS.rst
odoo/addons/stock_picking_batch_extended/readme/DESCRIPTION.rst
odoo/addons/stock_picking_batch_extended/report/__init__.py
odoo/addons/stock_picking_batch_extended/report/batch_report.py
odoo/addons/stock_picking_batch_extended/static/batch_form.png
odoo/addons/stock_picking_batch_extended/static/batch_form_operation.png
odoo/addons/stock_picking_batch_extended/static/batch_wizard.png
odoo/addons/stock_picking_batch_extended/static/stock_picking_list.png
odoo/addons/stock_picking_batch_extended/static/description/icon.png
odoo/addons/stock_picking_batch_extended/static/description/index.html
odoo12_addon_stock_picking_batch_extended-12.0.1.3.1.dist-info/METADATA
odoo12_addon_stock_picking_batch_extended-12.0.1.3.1.dist-info/WHEEL
odoo12_addon_stock_picking_batch_extended-12.0.1.3.1.dist-info/top_level.txt
odoo12_addon_stock_picking_batch_extended-12.0.1.3.1.dist-info/RECORD
