Metadata-Version: 2.1
Name: odoo12-addon-stock-picking-batch-extended
Version: 12.0.1.3.1
Summary: Allows manage a lot of pickings in batch
Home-page: https://github.com/OCA/stock-logistics-workflow
Author: Camptocamp, Tecnativa, Odoo Community Association (OCA)
Author-email: support@odoo-community.org
License: AGPL-3
Platform: UNKNOWN
Classifier: Programming Language :: Python
Classifier: Framework :: Odoo
Classifier: Framework :: Odoo :: 12.0
Classifier: License :: OSI Approved :: GNU Affero General Public License v3
Requires-Python: >=3.5
Requires-Dist: odoo12-addon-stock-picking-mass-action
Requires-Dist: odoo (<12.1dev,>=12.0a)
